README.md
setup.py
stepio/__init__.py
stepio/asset_parser.py
stepio.egg-info/PKG-INFO
stepio.egg-info/SOURCES.txt
stepio.egg-info/dependency_links.txt
stepio.egg-info/not-zip-safe
stepio.egg-info/top_level.txt
test/test_stepio.py