Metadata-Version: 1.0
Name: stepio
Version: 0.2
Summary: Asset parser for Step.investables and Step.deliverables on Infinity (infty.xyz).
Home-page: https://github.com/WeFindX/StepIO
Author: Mindey I.
Author-email: mindey@infty.xyz
License: MIT
Platform: UNKNOWN
